TeamsNotificationSubsystem/TeamsNotifier.py
TeamsNotificationSubsystem/__init__.py
TeamsNotificationSubsystem/Resources/BasicCard.json
TeamsNotificationSubsystem/Resources/ErrorCard.json
TeamsNotificationSubsystem/Resources/StandardCard.json
TeamsNotificationSubsystem/Resources/WarningCard.json
covenirbpo_package_teamsnotificationsubsystem-1.0.0.dist-info/METADATA
covenirbpo_package_teamsnotificationsubsystem-1.0.0.dist-info/WHEEL
covenirbpo_package_teamsnotificationsubsystem-1.0.0.dist-info/licenses/LICENSE
covenirbpo_package_teamsnotificationsubsystem-1.0.0.dist-info/RECORD
