Metadata-Version: 2.1
Name: CovenirBPO.package.TeamsNotificationSubsystem
Version: 1.0.0
Summary: A small package that allows for the transmission of teams notifications
Author-email: "Joshua H. Santiago" <joshman1019@gmail.com>
License-File: LICENSE
Classifier: License :: OSI Approved :: MIT License
Classifier: Operating System :: OS Independent
Classifier: Programming Language :: Python :: 3
Requires-Python: >=3.12.1
